# javap

```java
package javap;

public class JavapTest {
    private static final int P1 = 1;
    public static final int P2 = 2;

    public static void main(String[] args) {
        int m = 0, n = 0;
        for (int i = 0; i < 10; i++) {
            m = m++;
            n = ++n;
        }
        System.out.println("m = " + m);
        System.out.println("n = " + n);
    }
}

```

## javap -help

```
wanzailin@lin:~/IdeaProjects/practice/target/classes/javap$javap -help
用法: javap <options> <classes>
其中, 可能的选项包括:
  -help  --help  -?        输出此用法消息
  -version                 版本信息
  -v  -verbose             输出附加信息
  -l                       输出行号和本地变量表
  -public                  仅显示公共类和成员
  -protected               显示受保护的/公共类和成员
  -package                 显示程序包/受保护的/公共类
                           和成员 (默认)
  -p  -private             显示所有类和成员
  -c                       对代码进行反汇编
  -s                       输出内部类型签名
  -sysinfo                 显示正在处理的类的
                           系统信息 (路径, 大小, 日期, MD5 散列)
  -constants               显示最终常量
  -classpath <path>        指定查找用户类文件的位置
  -cp <path>               指定查找用户类文件的位置
  -bootclasspath <path>    覆盖引导类文件的位置
```

## javap -version
```
wanzailin@lin:~/IdeaProjects/practice/target/classes/javap$javap -version
1.8.0_152
```

## javap -p JavapTest.class
`-p 显示成员大于private的成员变量，方法`

```
wanzailin@lin:~/IdeaProjects/practice/target/classes/javap$javap -p JavapTest.class
Compiled from "JavapTest.java"
public class javap.JavapTest {
  private static final int P1;
  public static final int P2;
  public javap.JavapTest();
  public static void main(java.lang.String[]);
}
```

## javap -public JavaTest.class
-p 显示成员大于public的成员变量，方法`
```
wanzailin@lin:~/IdeaProjects/practice/target/classes/javap$javap -public JavapTest.class
Compiled from "JavapTest.java"
public class javap.JavapTest {
  public static final int P2;
  public javap.JavapTest();
  public static void main(java.lang.String[]);
}
```

## javap -protected JavapTest.class
`-p 显示成员大于protected的成员变量，方法`
```
wanzailin@lin:~/IdeaProjects/practice/target/classes/javap$javap -protected JavapTest.class
Compiled from "JavapTest.java"
public class javap.JavapTest {
  public static final int P2;
  public javap.JavapTest();
  public static void main(java.lang.String[]);
}
```

## javap -l JavapTest.class
```
wanzailin@lin:~/IdeaProjects/practice/target/classes/javap$javap -l JavapTest.class
Compiled from "JavapTest.java"
public class javap.JavapTest {
  public static final int P2;

  public javap.JavapTest();
    LineNumberTable:
      line 3: 0
    LocalVariableTable:
      Start  Length  Slot  Name   Signature
          0       5     0  this   Ljavap/JavapTest;

  public static void main(java.lang.String[]);
    LineNumberTable:
      line 8: 0
      line 9: 4
      line 10: 12
      line 11: 17
      line 9: 22
      line 13: 28
      line 14: 53
      line 15: 78
    LocalVariableTable:
      Start  Length  Slot  Name   Signature
          6      22     3     i   I
          0      79     0  args   [Ljava/lang/String;
          2      77     1     m   I
          4      75     2     n   I
}
```

## javap -package JavapTest.class
```
wanzailin@lin:~/IdeaProjects/practice/target/classes/javap$javap -package JavapTest.class
Compiled from "JavapTest.java"
public class javap.JavapTest {
  public static final int P2;
  public javap.JavapTest();
  public static void main(java.lang.String[]);
}
```

## javap -v JavapTest.class > a.txt

+ 我将它显示在a.txt中 后续理解

```
Classfile /Users/wanzailin/IdeaProjects/practice/target/classes/javap/JavapTest.class
  Last modified 2018-2-1; size 972 bytes
  MD5 checksum ad82a70601e0d6a3ab107d189cd87045
  Compiled from "JavapTest.java"
public class javap.JavapTest
  minor version: 0
  major version: 52
  flags: ACC_PUBLIC, ACC_SUPER
Constant pool:
   #1 = Methodref          #12.#36        // java/lang/Object."<init>":()V
   #2 = Fieldref           #37.#38        // java/lang/System.out:Ljava/io/PrintStream;
   #3 = Class              #39            // java/lang/StringBuilder
   #4 = Methodref          #3.#36         // java/lang/StringBuilder."<init>":()V
   #5 = String             #40            // m =
   #6 = Methodref          #3.#41         // java/lang/StringBuilder.append:(Ljava/lang/String;)Ljava/lang/StringBuilder;
   #7 = Methodref          #3.#42         // java/lang/StringBuilder.append:(I)Ljava/lang/StringBuilder;
   #8 = Methodref          #3.#43         // java/lang/StringBuilder.toString:()Ljava/lang/String;
   #9 = Methodref          #44.#45        // java/io/PrintStream.println:(Ljava/lang/String;)V
  #10 = String             #46            // n =
  #11 = Class              #47            // javap/JavapTest
  #12 = Class              #48            // java/lang/Object
  #13 = Utf8               P1
  #14 = Utf8               I
  #15 = Utf8               ConstantValue
  #16 = Integer            1
  #17 = Utf8               P2
  #18 = Integer            2
  #19 = Utf8               <init>
  #20 = Utf8               ()V
  #21 = Utf8               Code
  #22 = Utf8               LineNumberTable
  #23 = Utf8               LocalVariableTable
  #24 = Utf8               this
  #25 = Utf8               Ljavap/JavapTest;
  #26 = Utf8               main
  #27 = Utf8               ([Ljava/lang/String;)V
  #28 = Utf8               i
  #29 = Utf8               args
  #30 = Utf8               [Ljava/lang/String;
  #31 = Utf8               m
  #32 = Utf8               n
  #33 = Utf8               StackMapTable
  #34 = Utf8               SourceFile
  #35 = Utf8               JavapTest.java
  #36 = NameAndType        #19:#20        // "<init>":()V
  #37 = Class              #49            // java/lang/System
  #38 = NameAndType        #50:#51        // out:Ljava/io/PrintStream;
  #39 = Utf8               java/lang/StringBuilder
  #40 = Utf8               m =
  #41 = NameAndType        #52:#53        // append:(Ljava/lang/String;)Ljava/lang/StringBuilder;
  #42 = NameAndType        #52:#54        // append:(I)Ljava/lang/StringBuilder;
  #43 = NameAndType        #55:#56        // toString:()Ljava/lang/String;
  #44 = Class              #57            // java/io/PrintStream
  #45 = NameAndType        #58:#59        // println:(Ljava/lang/String;)V
  #46 = Utf8               n =
  #47 = Utf8               javap/JavapTest
  #48 = Utf8               java/lang/Object
  #49 = Utf8               java/lang/System
  #50 = Utf8               out
  #51 = Utf8               Ljava/io/PrintStream;
  #52 = Utf8               append
  #53 = Utf8               (Ljava/lang/String;)Ljava/lang/StringBuilder;
  #54 = Utf8               (I)Ljava/lang/StringBuilder;
  #55 = Utf8               toString
  #56 = Utf8               ()Ljava/lang/String;
  #57 = Utf8               java/io/PrintStream
  #58 = Utf8               println
  #59 = Utf8               (Ljava/lang/String;)V
{
  public static final int P2;
    descriptor: I
    flags: ACC_PUBLIC, ACC_STATIC, ACC_FINAL
    ConstantValue: int 2

  public javap.JavapTest();
    descriptor: ()V
    flags: ACC_PUBLIC
    Code:
      stack=1, locals=1, args_size=1
         0: aload_0
         1: invokespecial #1                  // Method java/lang/Object."<init>":()V
         4: return
      LineNumberTable:
        line 3: 0
      LocalVariableTable:
        Start  Length  Slot  Name   Signature
            0       5     0  this   Ljavap/JavapTest;

  public static void main(java.lang.String[]);
    descriptor: ([Ljava/lang/String;)V
    flags: ACC_PUBLIC, ACC_STATIC
    Code:
      stack=3, locals=4, args_size=1
         0: iconst_0
         1: istore_1
         2: iconst_0
         3: istore_2
         4: iconst_0
         5: istore_3
         6: iload_3
         7: bipush        10
         9: if_icmpge     28
        12: iload_1
        13: iinc          1, 1
        16: istore_1
        17: iinc          2, 1
        20: iload_2
        21: istore_2
        22: iinc          3, 1
        25: goto          6
        28: getstatic     #2                  // Field java/lang/System.out:Ljava/io/PrintStream;
        31: new           #3                  // class java/lang/StringBuilder
        34: dup
        35: invokespecial #4                  // Method java/lang/StringBuilder."<init>":()V
        38: ldc           #5                  // String m =
        40: invokevirtual #6                  // Method java/lang/StringBuilder.append:(Ljava/lang/String;)Ljava/lang/StringBuilder;
        43: iload_1
        44: invokevirtual #7                  // Method java/lang/StringBuilder.append:(I)Ljava/lang/StringBuilder;
        47: invokevirtual #8                  // Method java/lang/StringBuilder.toString:()Ljava/lang/String;
        50: invokevirtual #9                  // Method java/io/PrintStream.println:(Ljava/lang/String;)V
        53: getstatic     #2                  // Field java/lang/System.out:Ljava/io/PrintStream;
        56: new           #3                  // class java/lang/StringBuilder
        59: dup
        60: invokespecial #4                  // Method java/lang/StringBuilder."<init>":()V
        63: ldc           #10                 // String n =
        65: invokevirtual #6                  // Method java/lang/StringBuilder.append:(Ljava/lang/String;)Ljava/lang/StringBuilder;
        68: iload_2
        69: invokevirtual #7                  // Method java/lang/StringBuilder.append:(I)Ljava/lang/StringBuilder;
        72: invokevirtual #8                  // Method java/lang/StringBuilder.toString:()Ljava/lang/String;
        75: invokevirtual #9                  // Method java/io/PrintStream.println:(Ljava/lang/String;)V
        78: return
      LineNumberTable:
        line 8: 0
        line 9: 4
        line 10: 12
        line 11: 17
        line 9: 22
        line 13: 28
        line 14: 53
        line 15: 78
      LocalVariableTable:
        Start  Length  Slot  Name   Signature
            6      22     3     i   I
            0      79     0  args   [Ljava/lang/String;
            2      77     1     m   I
            4      75     2     n   I
      StackMapTable: number_of_entries = 2
        frame_type = 254 /* append */
          offset_delta = 6
          locals = [ int, int, int ]
        frame_type = 250 /* chop */
          offset_delta = 21
}
SourceFile: "JavapTest.java"

```
## javap -constants JavapTest.class

```
wanzailin@lin:~/IdeaProjects/practice/target/classes/javap$javap -constants JavapTest.class
Compiled from "JavapTest.java"
public class javap.JavapTest {
  public static final int P2 = 2;
  public javap.JavapTest();
  public static void main(java.lang.String[]);
}
```


















